memory_manager/__init__.py
memory_manager/core.py
memory_manager-0.31.dist-info/METADATA
memory_manager-0.31.dist-info/WHEEL
memory_manager-0.31.dist-info/top_level.txt
memory_manager-0.31.dist-info/RECORD
