Metadata-Version: 2.1
Name: memory_manager
Version: 0.31
Summary: Memory manager for hooking and manipulating game memory
Author: FURYMOB
Author-email: 
Keywords: videogame,memory,addresses,manager,triggers
Classifier: Programming Language :: Python :: 3
Classifier: License :: OSI Approved :: MIT License
Classifier: Operating System :: OS Independent
Requires-Python: >=3.6
Requires-Dist: pymem
